pylatexenc/__init__.py
pylatexenc/latex2text.py
pylatexenc/latexencode.py
pylatexenc/latexwalker.py
pylatexenc/version.py
pylatexenc-1.0.post1.dist-info/DESCRIPTION.rst
pylatexenc-1.0.post1.dist-info/METADATA
pylatexenc-1.0.post1.dist-info/metadata.json
pylatexenc-1.0.post1.dist-info/RECORD
pylatexenc-1.0.post1.dist-info/top_level.txt
pylatexenc-1.0.post1.dist-info/WHEEL
