Metadata-Version: 2.0
Name: pylatexenc
Version: 1.0.post1
Summary: Python library for encoding unicode to latex and for parsing LaTeX to generate unicode text
Home-page: https://github.com/phfaist/pylatexenc
Author: Philippe Faist
Author-email: philippe.faist@bluewin.ch
License: MIT
Keywords: latex text unicode encode parse expression
Platform: UNKNOWN
Classifier: Development Status :: 5 - Production/Stable
Classifier: License :: OSI Approved :: MIT License
Classifier: Programming Language :: Python
Classifier: Operating System :: OS Independent
Classifier: Intended Audience :: Developers
Classifier: Topic :: Scientific/Engineering
Classifier: Topic :: Text Processing :: General
Classifier: Topic :: Text Processing :: Markup :: LaTeX
